{"I": 1, "don't": 2, "have": 3, "a": 4, "clue": 5, "know": 6, "no": 7, "idea": 8, "may": 9, "agree": 10, "might": 11, "think": 12, "so": 13, "I'm": 14, "not": 15, "sure": 16, "if": 17, "dunno": 18, "maybe": 19, "meh": 20, "perhaps": 21, "possibly": 22, "unsure": 23, "wait": 24, "changed": 25, "my": 26, "mind": 27, "absolutely": 28, "belay": 29, "that": 30, "cut": 31, "it": 32, "out": 33, "do": 34, "anything": 35, "forget": 36, "never": 37, "thanks": 38, "way": 39, "on": 40, "second": 41, "thought,": 42, "please": 43, "scratch": 44, "cancel": 45, "denied": 46, "disengage": 47, "end": 48, "exit": 49, "halt": 50, "n": 51, "nah": 52, "nay": 53, "neg": 54, "negative": 55, "negatory": 56, "nein": 57, "nevermind": 58, "nope": 59, "nyet": 60, "quit": 61, "skip": 62, "stop": 63, "aye": 64, "carry": 65, "get": 66, "with": 67, "then": 68, "go": 69, "ahead": 70, "i": 71, "make": 72, "happen": 73, "most": 74, "assuredly": 75, "perfect,": 76, "rock": 77, "that's": 78, "correct": 79, "right": 80, "uh": 81, "huh": 82, "yeah,": 83, "yes,": 84, "you": 85, "got": 86, "affirmative": 87, "alright": 88, "certainly": 89, "confirmed": 90, "continue": 91, "da": 92, "good": 93, "hooray": 94, "ja": 95, "ok": 96, "okay": 97, "proceed": 98, "righto": 99, "totally": 100, "true": 101, "y": 102, "ya": 103, "yay": 104, "yea": 105, "yeah": 106, "yep": 107, "yeppers": 108, "yes": 109, "why": 110, "let's": 111, "would": 112, "love": 113, "to": 114, "am": 115, "in": 116, "interested": 117, "free": 118, "want": 119, "feel": 120, "won't": 121, "be": 122, "here": 123, "Maybe": 124, "can": 125, "will": 126, "tell": 127, "about": 128, "let": 129, "It": 130, "interesting": 131, "contact": 132}